{"code":200,"success":true,"data":{"total":11,"records":[{"recordId":"recjppDJKMdzB","createdAt":1692784516000,"updatedAt":1692784516000,"fields":{"类型|type":"系统指令","指令名称|name":"帮助","说明|desc":"获得操作指令集"}},{"recordId":"recVVFq037aFR","createdAt":1692784516000,"updatedAt":1692784516000,"fields":{"类型|type":"系统指令","指令名称|name":"更新配置","说明|desc":"更新系统配置，更改配置后需主动更新一次配置配置才会生效"}},{"recordId":"recYVi2GK5gsg","createdAt":1692784516000,"updatedAt":1692784516000,"fields":{"类型|type":"系统指令","指令名称|name":"更新定时提醒","说明|desc":"更新定时提醒任务"}},{"recordId":"rech6ge4VpbRR","createdAt":1692784516000,"updatedAt":1692784516000,"fields":{"类型|type":"系统指令","指令名称|name":"更新通讯录","说明|desc":"更新机器人的群列表和好友列表"}},{"recordId":"recDZiUv3fLOp","createdAt":1692784516000,"updatedAt":1692784516000,"fields":{"类型|type":"系统指令","指令名称|name":"下载通讯录","说明|desc":"下载通讯录xlsx表"}},{"recordId":"recLHUzfXxIKf","createdAt":1692784516000,"updatedAt":1692784516000,"fields":{"类型|type":"系统指令","指令名称|name":"更新白名单","说明|desc":"更新群白名单，白名单变动时需主动更新白名单"}},{"recordId":"recXvdoAEg2Hf","createdAt":1692784516000,"updatedAt":1692784516000,"fields":{"类型|type":"系统指令","指令名称|name":"下载通知模板","说明|desc":"下载通知模板"}},{"recordId":"recnNMmuQypon","createdAt":1692784516000,"updatedAt":1692784516000,"fields":{"类型|type":"群指令","指令名称|name":"启用问答","说明|desc":"TBD当前群启用智能问答"}},{"recordId":"recZR7uraq0WE","createdAt":1692784516000,"updatedAt":1692784516000,"fields":{"类型|type":"群指令","指令名称|name":"关闭问答","说明|desc":"TBD当前群关闭智能问答"}},{"recordId":"rec4TtNl7lZEa","createdAt":1692784516000,"updatedAt":1692784516000,"fields":{"类型|type":"等于关键字","指令名称|name":"车找人","说明|desc":"筛选车找人信息"}},{"recordId":"rec8K8fn2nTcI","createdAt":1692784518000,"updatedAt":1692784518000,"fields":{"类型|type":"包含关键字","指令名称|name":"人找车","说明|desc":"匹配人找车信息"}}],"pageNum":1,"pageSize":11},"message":"SUCCESS"}